charaiPY/AsyncPyCAI2.py
charaiPY/__init__.py
charaiPY/erorr.py
charaiPY/nPyCAI2.py
PyCAI2-2.0.4.dist-info/METADATA
PyCAI2-2.0.4.dist-info/WHEEL
PyCAI2-2.0.4.dist-info/top_level.txt
PyCAI2-2.0.4.dist-info/RECORD
