Metadata-Version: 2.1
Name: PyCAI2
Version: 2.0.4
Summary: Unofficial Python wrapper for character ai, More Easy to use
Author: Tokai Faclo
Author-email: otsronca@gmail.com
Keywords: python,AI,chat bot,character ai
Classifier: Development Status :: 1 - Planning
Classifier: Intended Audience :: Developers
Classifier: Programming Language :: Python :: 3
Classifier: Operating System :: Microsoft :: Windows
Requires-Dist: tls-client
Requires-Dist: websockets
Requires-Dist: easygoogletranslate
